{
  "epoch": 16,
  "epochs": 20,
  "val_loss": 1.814894,
  "val_policy_loss": 1.800047,
  "val_value_loss": 0.014847,
  "train_loss": 1.595352,
  "positions": 6993,
  "batch_size": 1024,
  "lr": 0.002,
  "device": "cuda",
  "resumed_from": "azloop_from_best_so_far_best",
  "seeded_from": "azloop_from_best_mcts100_best",
  "data_run": "azloop_from_best_so_far",
  "data_runs": [
    "azloop_from_best_so_far"
  ],
  "data_shards": 4,
  "data_shard_names": [
    "azloop_from_best_so_far/shard_0000.npz",
    "azloop_from_best_so_far/shard_0001.npz",
    "azloop_from_best_so_far/shard_0002.npz",
    "azloop_from_best_so_far/shard_0003.npz"
  ],
  "data_sha": "eaea5f81cc472e31",
  "arch": "az",
  "channels": 128,
  "blocks": 10,
  "promoted_from": "azloop_from_best_so_far_candidate",
  "arena": {
    "games": 20,
    "wins": 3,
    "draws": 16,
    "losses": 1,
    "score": 0.55,
    "elapsed": 47.09481216100539
  },
  "promoted_at": "2026-07-13 05:15:54",
  "elo": -663.0
}